tdfl/__init__.py
tdfl/array.py
tdfl/config.toml
tdfl/dataframe.py
tdfl/parsing.py
tdfl/utils.py
tdfl-0.1.15.dist-info/LICENSE
tdfl-0.1.15.dist-info/METADATA
tdfl-0.1.15.dist-info/WHEEL
tdfl-0.1.15.dist-info/top_level.txt
tdfl-0.1.15.dist-info/RECORD
