Metadata-Version: 2.1
Name: tdfl
Version: 0.1.15
Summary: DataFrame supporting PyTorch Tensor columns.
Author: Ho Yin Chau
License: MIT License
Project-URL: repository, https://github.com/hchau630/tdfl
Keywords: PyTorch,torch,pandas,DataFrame,SQLite,sqlite3
Classifier: Development Status :: 2 - Pre-Alpha
Classifier: License :: OSI Approved :: MIT License
Classifier: Natural Language :: English
Classifier: Operating System :: OS Independent
Classifier: Programming Language :: Python :: 3.9
Requires-Python: >=3.9
License-File: LICENSE
Requires-Dist: numpy >=1.23
Requires-Dist: torch >=2.1.0
Requires-Dist: pandas
Requires-Dist: addict
Requires-Dist: beautifulsoup4
Requires-Dist: hyclib[ml] >=0.1.30
